odoo9_addon_sale_automatic_workflow_payment_mode-9.0.2.0.0.99.dev20-py3.8-nspkg.pth
odoo_addons/sale_automatic_workflow_payment_mode/README.rst
odoo_addons/sale_automatic_workflow_payment_mode/__init__.py
odoo_addons/sale_automatic_workflow_payment_mode/__openerp__.py
odoo_addons/sale_automatic_workflow_payment_mode/data/automatic_workflow_data.xml
odoo_addons/sale_automatic_workflow_payment_mode/i18n/ca.po
odoo_addons/sale_automatic_workflow_payment_mode/i18n/de.po
odoo_addons/sale_automatic_workflow_payment_mode/i18n/es.po
odoo_addons/sale_automatic_workflow_payment_mode/i18n/es_ES.po
odoo_addons/sale_automatic_workflow_payment_mode/i18n/fi.po
odoo_addons/sale_automatic_workflow_payment_mode/i18n/fr.po
odoo_addons/sale_automatic_workflow_payment_mode/i18n/hr.po
odoo_addons/sale_automatic_workflow_payment_mode/i18n/hu.po
odoo_addons/sale_automatic_workflow_payment_mode/i18n/it.po
odoo_addons/sale_automatic_workflow_payment_mode/i18n/nl.po
odoo_addons/sale_automatic_workflow_payment_mode/i18n/nl_NL.po
odoo_addons/sale_automatic_workflow_payment_mode/i18n/pt_BR.po
odoo_addons/sale_automatic_workflow_payment_mode/i18n/ro.po
odoo_addons/sale_automatic_workflow_payment_mode/i18n/sale_automatic_workflow_payment_mode.pot
odoo_addons/sale_automatic_workflow_payment_mode/i18n/sk.po
odoo_addons/sale_automatic_workflow_payment_mode/i18n/sl.po
odoo_addons/sale_automatic_workflow_payment_mode/i18n/tr.po
odoo_addons/sale_automatic_workflow_payment_mode/i18n/tr_TR.po
odoo_addons/sale_automatic_workflow_payment_mode/i18n/zh_CN.po
odoo_addons/sale_automatic_workflow_payment_mode/models/__init__.py
odoo_addons/sale_automatic_workflow_payment_mode/models/account_payment_mode.py
odoo_addons/sale_automatic_workflow_payment_mode/models/automatic_workflow_job.py
odoo_addons/sale_automatic_workflow_payment_mode/models/sale_order.py
odoo_addons/sale_automatic_workflow_payment_mode/models/sale_workflow_process.py
odoo_addons/sale_automatic_workflow_payment_mode/static/description/icon.png
odoo9_addon_sale_automatic_workflow_payment_mode-9.0.2.0.0.99.dev20.dist-info/METADATA
odoo9_addon_sale_automatic_workflow_payment_mode-9.0.2.0.0.99.dev20.dist-info/WHEEL
odoo9_addon_sale_automatic_workflow_payment_mode-9.0.2.0.0.99.dev20.dist-info/namespace_packages.txt
odoo9_addon_sale_automatic_workflow_payment_mode-9.0.2.0.0.99.dev20.dist-info/top_level.txt
odoo9_addon_sale_automatic_workflow_payment_mode-9.0.2.0.0.99.dev20.dist-info/RECORD
